Built/__init__.py
Built/stc.py
Math/__init__.py
Math/area.py
Math/symbol.py
Math/volume.py
CogsL-0.0.1.dist-info/LICENSE
CogsL-0.0.1.dist-info/METADATA
CogsL-0.0.1.dist-info/WHEEL
CogsL-0.0.1.dist-info/top_level.txt
CogsL-0.0.1.dist-info/RECORD
