Metadata-Version: 2.1
Name: CogsL
Version: 0.0.1
Summary: An interpretive language
Author: GitHub-Buelie
Author-email: yydshmcl@outlook.com
License: MIT License
Requires: random
Requires: matplotlib
Requires: os
License-File: LICENSE
